HcoopMeetbot/.gitignore
HcoopMeetbot/__init__.py
HcoopMeetbot/config.py
HcoopMeetbot/plugin.py
HcoopMeetbot/test.py
hcoopmeetbotlogic/__init__.py
hcoopmeetbotlogic/cli.py
hcoopmeetbotlogic/command.py
hcoopmeetbotlogic/config.py
hcoopmeetbotlogic/dateutil.py
hcoopmeetbotlogic/handler.py
hcoopmeetbotlogic/interface.py
hcoopmeetbotlogic/location.py
hcoopmeetbotlogic/meeting.py
hcoopmeetbotlogic/py.typed
hcoopmeetbotlogic/release.py
hcoopmeetbotlogic/state.py
hcoopmeetbotlogic/writer.py
hcoopmeetbotlogic/templates/log.html
hcoopmeetbotlogic/templates/minutes.html
hcoop_meetbot-0.8.1.dist-info/METADATA
hcoop_meetbot-0.8.1.dist-info/WHEEL
hcoop_meetbot-0.8.1.dist-info/entry_points.txt
hcoop_meetbot-0.8.1.dist-info/licenses/LICENSE
hcoop_meetbot-0.8.1.dist-info/licenses/NOTICE
hcoop_meetbot-0.8.1.dist-info/RECORD
