Metadata-Version: 2.4
Name: hcoop-meetbot
Version: 0.8.1
Summary: Plugin for Limnoria to help run IRC meetings
Project-URL: Homepage, https://pypi.org/project/hcoop-meetbot/
Project-URL: Repository, https://github.com/pronovic/hcoop-meetbot
Project-URL: Changelog, https://github.com/pronovic/hcoop-meetbot/releases
Project-URL: Documentation, https://hcoop-meetbot.readthedocs.io/en/stable/
Project-URL: Issues, https://github.com/pronovic/hcoop-meetbot/issues
Author-email: "Kenneth J. Pronovici" <pronovic@ieee.org>
License-Expression: Apache-2.0
License-File: LICENSE
License-File: NOTICE
Classifier: Environment :: Console
Classifier: Intended Audience :: System Administrators
Classifier: Natural Language :: English
Classifier: Operating System :: OS Independent
Classifier: Programming Language :: Python :: 3
Classifier: Programming Language :: Python :: 3.11
Classifier: Programming Language :: Python :: 3.12
Classifier: Programming Language :: Python :: 3.13
Classifier: Programming Language :: Python :: 3.14
Classifier: Topic :: Communications :: Chat :: Internet Relay Chat
Classifier: Topic :: Utilities
Requires-Python: <4,>=3.11
Requires-Dist: attrs>=24.2.0
Requires-Dist: cattrs>=24.1.2
Requires-Dist: click<9.0.0,>=8.1.7
Requires-Dist: genshi<0.8.0,>=0.7.7
Requires-Dist: limnoria>=2023.09.24
Requires-Dist: pytz>=2023.3.post1
Provides-Extra: docs
Requires-Dist: sphinx-autoapi<4.0.0,>=3.3.3; extra == 'docs'
Requires-Dist: sphinx<9.0.0,>=8.1.3; extra == 'docs'
